README.md
setup.py
n2yoasync/__init__.py
n2yoasync.egg-info/PKG-INFO
n2yoasync.egg-info/SOURCES.txt
n2yoasync.egg-info/dependency_links.txt
n2yoasync.egg-info/top_level.txt