Metadata-Version: 2.1
Name: n2yoasync
Version: 0.0.4
Summary: Async Python wrapper for the N2YO API
Home-page: https://github.com/djtimca/n2yo-api
Author: Tim Empringham
Author-email: tim.empringham@live.ca
License: UNKNOWN
Keywords: N2YO,Satellite
Platform: UNKNOWN
Classifier: Programming Language :: Python :: 3
Classifier: License :: OSI Approved :: MIT License
Classifier: Operating System :: OS Independent
